<?xml version="1.0" encoding="utf-8"?>
<Defs>

	<ConceptDef>
		<defName>O21_Concept_AutomatedProduction</defName>
		<label>[O21] Production tab</label>
		<needsOpportunity>true</needsOpportunity>
		<opportunityDecays>false</opportunityDecays>
		<priority>50</priority>
		<highlightTags>
			<li>O21_Automated-Production-Closed</li>
		</highlightTags>
		<helpText>To make automated producers work, select the building and open the Production tab. Here you can tell it what recipe it uses, this can vary from mining, crafting to even creating new pawns depending on the building. The repeat and cancel buttons should be fairly self-explanitory.</helpText>
  	</ConceptDef>

</Defs>
